{"is_source_file": true, "format": "JavaScript (React JSX)", "description": "This source file defines a React functional component for a Reset Password page, including UI layout and form elements.", "external_files": ["../../components/layout/AppShell", "../../components/common/Button"], "external_methods": ["Button (constructor or export from Button module)"], "published": ["ResetPassword"], "classes": [], "methods": [{"name": "ResetPassword()", "description": "React functional component rendering the Reset Password page with a form and layout.", "scope": "", "scopeKind": ""}], "calls": ["React", "AppShell", "Button"], "search-terms": ["ResetPassword", "React component", "jsx form", "Password reset page", "Auth page"], "state": 2, "file_id": 35, "knowledge_revision": 78, "git_revision": "", "ctags": [{"_type": "tag", "name": "ResetPassword", "path": "/home/kavia/workspace/code-generation/universal-application-suite-242-218/frontend_app/src/pages/Auth/ResetPassword.jsx", "pattern": "/^export default function ResetPassword() {$/", "language": "JavaScript", "kind": "function", "signature": "()"}], "hash": "bdba31c3dc12921226657675072b0fc7", "format-version": 4, "code-base-name": "frontend_app", "filename": "frontend_app/src/pages/Auth/ResetPassword.jsx", "revision_history": [{"78": ""}]}