{"is_source_file": true, "format": "JavaScript", "description": "This file sets up testing utilities for a JavaScript project, specifically importing jest-dom for extended DOM assertions in tests.", "external_files": ["@testing-library/jest-dom"], "external_methods": [], "published": [], "classes": [], "methods": [], "calls": ["import '@testing-library/jest-dom'"], "search-terms": ["setupTests.js", "jest-dom", "testing-library", "test setup"], "state": 2, "file_id": 7, "knowledge_revision": 23, "git_revision": "2ab150be0d51a60fce3e3de7473368e720577813", "ctags": [], "hash": "1a77571e1a8cf36018a41bcedf60db75", "format-version": 4, "code-base-name": "frontend_app", "filename": "frontend_app/src/setupTests.js", "revision_history": [{"23": "2ab150be0d51a60fce3e3de7473368e720577813"}]}